pygenplot/__init__.py
pygenplot/__pkginfo__.py
pygenplot/data/__init__.py
pygenplot/data/units.py
pygenplot/data/units.yml
pygenplot/dialogs/__init__.py
pygenplot/dialogs/about_dialog.py
pygenplot/dialogs/cross_viewer_dialog.py
pygenplot/dialogs/data_viewer_1d_dialog.py
pygenplot/dialogs/data_viewer_nd_dialog.py
pygenplot/dialogs/inspect_data_dialog.py
pygenplot/dialogs/plot_1d_axis_settings_dialog.py
pygenplot/dialogs/plot_1d_general_settings_dialog.py
pygenplot/dialogs/plot_1d_lines_settings_dialog.py
pygenplot/dialogs/plot_2d_general_settings_dialog.py
pygenplot/dialogs/plot_2d_image_settings_dialog.py
pygenplot/dialogs/plot_nd_axis_settings_dialog.py
pygenplot/dialogs/plot_nd_general_settings_dialog.py
pygenplot/dialogs/plot_nd_image_settings_dialog.py
pygenplot/dialogs/radial_integration_dialog.py
pygenplot/dialogs/roi_dialog.py
pygenplot/dialogs/slice_viewer_dialog.py
pygenplot/dialogs/units_editor_dialog.py
pygenplot/dialogs/viewer_1d_dialog.py
pygenplot/handlers/__init__.py
pygenplot/handlers/logger_popup.py
pygenplot/handlers/logger_widget.py
pygenplot/icons/__init__.py
pygenplot/icons/about.png
pygenplot/icons/axis.png
pygenplot/icons/browse.png
pygenplot/icons/checked.png
pygenplot/icons/clear.png
pygenplot/icons/clipboard.png
pygenplot/icons/cross.png
pygenplot/icons/current_tab.png
pygenplot/icons/data.png
pygenplot/icons/exit.png
pygenplot/icons/experiment.png
pygenplot/icons/export.png
pygenplot/icons/generate_drill.png
pygenplot/icons/group.png
pygenplot/icons/hdf.png
pygenplot/icons/image.png
pygenplot/icons/line.png
pygenplot/icons/load.png
pygenplot/icons/nd_slice.png
pygenplot/icons/new_tab.png
pygenplot/icons/plot.png
pygenplot/icons/plot_1d.png
pygenplot/icons/plot_2d.png
pygenplot/icons/plot_nd.png
pygenplot/icons/plus.png
pygenplot/icons/print.png
pygenplot/icons/process.png
pygenplot/icons/quickview.png
pygenplot/icons/radial_integration.png
pygenplot/icons/roi.png
pygenplot/icons/run.png
pygenplot/icons/settings.png
pygenplot-0.0.5.dist-info/LICENSE
pygenplot-0.0.5.dist-info/METADATA
pygenplot-0.0.5.dist-info/WHEEL
pygenplot-0.0.5.dist-info/top_level.txt
pygenplot-0.0.5.dist-info/RECORD
